{
  "schemaVersion": "openclaw-artifact-v1",
  "runId": "uapt-university-of-liverpool-20260514",
  "artifacts": [
    {
      "schemaVersion": "openclaw-artifact-v1",
      "runId": "uapt-university-of-liverpool-20260514",
      "artifactType": "source_discovery_trace",
      "traceId": "trace-liverpool-20260514",
      "entityType": "university",
      "entitySlug": "university-of-liverpool",
      "startedAt": "2026-05-14T22:20:00.000Z",
      "endedAt": "2026-05-14T22:48:00.000Z",
      "methodsAttempted": [
        {
          "method": "public_web_search",
          "query": "site:liverpool.ac.uk University of Liverpool generative AI policy students assessment academic integrity artificial intelligence",
          "domain": "liverpool.ac.uk",
          "resultCount": 8,
          "notes": "Firecrawl search located the central AI at Liverpool policy area, learning/teaching/assessment guidance, central PDFs, a student news post, and a repository research poster."
        },
        {
          "method": "public_web_search",
          "query": "site:liverpool.ac.uk University of Liverpool AI data protection security Microsoft Copilot generative AI policies guidance",
          "domain": "liverpool.ac.uk",
          "resultCount": 8,
          "notes": "Firecrawl search located the central policies and guidance hub, legal/security/data-protection page, and the Foundations of AI page describing Microsoft Copilot."
        },
        {
          "method": "link_traversal",
          "domain": "www.liverpool.ac.uk",
          "resultCount": 6,
          "notes": "Followed official AI at Liverpool links among policies and guidance, golden rules, learning/teaching/assessment, legal/security/data protection, foundations, and research guidance."
        }
      ],
      "noSourceEscalationCompleted": false,
      "candidateIds": [
        "sc-liverpool-ai-policies-hub",
        "sc-liverpool-genai-lta-guidance",
        "sc-liverpool-legal-security-data",
        "sc-liverpool-foundations-copilot",
        "sc-liverpool-golden-rules",
        "sc-liverpool-research-guidance",
        "sc-liverpool-news-academic-integrity",
        "sc-liverpool-repository-genai-assessment-poster"
      ],
      "rejectionIds": [
        "sr-liverpool-news-academic-integrity",
        "sr-liverpool-repository-genai-assessment-poster"
      ],
      "summary": "Official-source discovery found a central University of Liverpool AI policy and guidance area with verified pages for golden rules, learning/teaching/assessment, legal/security/data protection, Microsoft Copilot, and research guidance. The older student news article and repository research poster were documented but rejected for current staged claims because they are not the central current policy/guidance pages."
    },
    {
      "schemaVersion": "openclaw-artifact-v1",
      "runId": "uapt-university-of-liverpool-20260514",
      "artifactType": "crawl_plan",
      "planId": "cp-liverpool-20260514",
      "createdAt": "2026-05-14T22:48:00.000Z",
      "createdBy": "openclaw-agent",
      "targets": [
        {
          "entityType": "university",
          "entitySlug": "university-of-liverpool",
          "sourceCandidateId": "sc-liverpool-ai-policies-hub",
          "sourceUrl": "https://www.liverpool.ac.uk/about/the-university/reports-policies-and-governance/ai-at-liverpool/policies-and-guidance/",
          "sourceTitle": "University of Liverpool policies and guidance on AI",
          "sourceLanguage": "en",
          "allowedFetchModes": [
            "http",
            "firecrawl"
          ],
          "expectedThemes": [
            "central AI guidance hub",
            "framework for exploration",
            "linked central guidance pages"
          ],
          "robotsPolicy": "respect"
        },
        {
          "entityType": "university",
          "entitySlug": "university-of-liverpool",
          "sourceCandidateId": "sc-liverpool-genai-lta-guidance",
          "sourceUrl": "https://www.liverpool.ac.uk/about/the-university/reports-policies-and-governance/ai-at-liverpool/policies-and-guidance/guidance-learning-teaching-and-assessment/",
          "sourceTitle": "University guidance on GenAI in learning, teaching and assessment",
          "sourceLanguage": "en",
          "allowedFetchModes": [
            "http",
            "firecrawl"
          ],
          "expectedThemes": [
            "learning teaching and assessment",
            "unacceptable education uses",
            "assessment regulatory boundary"
          ],
          "robotsPolicy": "respect"
        },
        {
          "entityType": "university",
          "entitySlug": "university-of-liverpool",
          "sourceCandidateId": "sc-liverpool-legal-security-data",
          "sourceUrl": "https://www.liverpool.ac.uk/about/the-university/reports-policies-and-governance/ai-at-liverpool/policies-and-guidance/legal-security-and-data-protection/",
          "sourceTitle": "Legal, security and data protection",
          "sourceLanguage": "en",
          "allowedFetchModes": [
            "http",
            "firecrawl"
          ],
          "expectedThemes": [
            "data protection",
            "security",
            "personal data restrictions"
          ],
          "robotsPolicy": "respect"
        },
        {
          "entityType": "university",
          "entitySlug": "university-of-liverpool",
          "sourceCandidateId": "sc-liverpool-foundations-copilot",
          "sourceUrl": "https://www.liverpool.ac.uk/about/the-university/reports-policies-and-governance/ai-at-liverpool/foundations-of-ai/",
          "sourceTitle": "Foundations of AI",
          "sourceLanguage": "en",
          "allowedFetchModes": [
            "http",
            "firecrawl"
          ],
          "expectedThemes": [
            "Microsoft Copilot",
            "endorsed tool",
            "enterprise data protection"
          ],
          "robotsPolicy": "respect"
        },
        {
          "entityType": "university",
          "entitySlug": "university-of-liverpool",
          "sourceCandidateId": "sc-liverpool-golden-rules",
          "sourceUrl": "https://www.liverpool.ac.uk/about/the-university/reports-policies-and-governance/ai-at-liverpool/policies-and-guidance/golden-rules/",
          "sourceTitle": "Golden rules",
          "sourceLanguage": "en",
          "allowedFetchModes": [
            "http",
            "firecrawl"
          ],
          "expectedThemes": [
            "support tool",
            "attribution",
            "protecting data",
            "verification"
          ],
          "robotsPolicy": "respect"
        },
        {
          "entityType": "university",
          "entitySlug": "university-of-liverpool",
          "sourceCandidateId": "sc-liverpool-research-guidance",
          "sourceUrl": "https://www.liverpool.ac.uk/about/the-university/reports-policies-and-governance/ai-at-liverpool/policies-and-guidance/guidance-for-research/",
          "sourceTitle": "University guidance on generative artificial intelligence for research",
          "sourceLanguage": "en",
          "allowedFetchModes": [
            "http",
            "firecrawl"
          ],
          "expectedThemes": [
            "research integrity",
            "transparency",
            "accountability",
            "inappropriate research uses"
          ],
          "robotsPolicy": "respect"
        }
      ],
      "stopConditions": [
        "Stop after central University of Liverpool AI pages support direct claim candidates.",
        "Do not infer binding university-wide policy from news, repository research posters, or page descriptions.",
        "Preserve original English evidence snippets and avoid promoting staged claims as canonical."
      ]
    },
    {
      "schemaVersion": "openclaw-artifact-v1",
      "runId": "uapt-university-of-liverpool-20260514",
      "artifactType": "source_candidate",
      "sourceCandidateId": "sc-liverpool-ai-policies-hub",
      "entityType": "university",
      "entitySlug": "university-of-liverpool",
      "sourceUrl": "https://www.liverpool.ac.uk/about/the-university/reports-policies-and-governance/ai-at-liverpool/policies-and-guidance/",
      "finalUrl": "https://www.liverpool.ac.uk/about/the-university/reports-policies-and-governance/ai-at-liverpool/policies-and-guidance/",
      "sourceTitle": "University of Liverpool policies and guidance on AI",
      "sourceLanguage": "en",
      "sourceType": "university_guidance",
      "discoveryMethod": "public_web_search",
      "queryUsed": "site:liverpool.ac.uk University of Liverpool generative AI policy students assessment academic integrity artificial intelligence",
      "discoveredAt": "2026-05-14T22:20:00.000Z",
      "officialDomainConfidence": 1,
      "aiRelevanceScore": 0.98,
      "policySpecificityScore": 0.92,
      "verificationStatus": "verified",
      "verifiedAt": "2026-05-14T22:48:00.000Z",
      "verificationNotes": "Official University of Liverpool central page collating AI policies and guidance across golden rules, legal/security/data protection, learning/teaching/assessment, and research.",
      "robotsPolicy": "respect"
    },
    {
      "schemaVersion": "openclaw-artifact-v1",
      "runId": "uapt-university-of-liverpool-20260514",
      "artifactType": "source_candidate",
      "sourceCandidateId": "sc-liverpool-genai-lta-guidance",
      "entityType": "university",
      "entitySlug": "university-of-liverpool",
      "sourceUrl": "https://www.liverpool.ac.uk/about/the-university/reports-policies-and-governance/ai-at-liverpool/policies-and-guidance/guidance-learning-teaching-and-assessment/",
      "finalUrl": "https://www.liverpool.ac.uk/about/the-university/reports-policies-and-governance/ai-at-liverpool/policies-and-guidance/guidance-learning-teaching-and-assessment/",
      "sourceTitle": "University guidance on GenAI in learning, teaching and assessment",
      "sourceLanguage": "en",
      "sourceType": "assessment_guidance",
      "discoveryMethod": "public_web_search",
      "queryUsed": "site:liverpool.ac.uk University of Liverpool generative AI policy students assessment academic integrity artificial intelligence",
      "discoveredAt": "2026-05-14T22:21:00.000Z",
      "officialDomainConfidence": 1,
      "aiRelevanceScore": 0.99,
      "policySpecificityScore": 0.95,
      "verificationStatus": "verified",
      "verifiedAt": "2026-05-14T22:48:00.000Z",
      "verificationNotes": "Official central page describing University guidance on GenAI in learning, teaching, and assessment, including unacceptable uses and the relationship to Appendix L of the Code of Practice on Assessment.",
      "robotsPolicy": "respect"
    },
    {
      "schemaVersion": "openclaw-artifact-v1",
      "runId": "uapt-university-of-liverpool-20260514",
      "artifactType": "source_candidate",
      "sourceCandidateId": "sc-liverpool-legal-security-data",
      "entityType": "university",
      "entitySlug": "university-of-liverpool",
      "sourceUrl": "https://www.liverpool.ac.uk/about/the-university/reports-policies-and-governance/ai-at-liverpool/policies-and-guidance/legal-security-and-data-protection/",
      "finalUrl": "https://www.liverpool.ac.uk/about/the-university/reports-policies-and-governance/ai-at-liverpool/policies-and-guidance/legal-security-and-data-protection/",
      "sourceTitle": "Legal, security and data protection",
      "sourceLanguage": "en",
      "sourceType": "it_security_privacy",
      "discoveryMethod": "public_web_search",
      "queryUsed": "site:liverpool.ac.uk University of Liverpool AI data protection security Microsoft Copilot generative AI policies guidance",
      "discoveredAt": "2026-05-14T22:23:00.000Z",
      "officialDomainConfidence": 1,
      "aiRelevanceScore": 0.97,
      "policySpecificityScore": 0.94,
      "verificationStatus": "verified",
      "verifiedAt": "2026-05-14T22:48:00.000Z",
      "verificationNotes": "Official central page with legal, security, and data-protection guidance for GenAI use.",
      "robotsPolicy": "respect"
    },
    {
      "schemaVersion": "openclaw-artifact-v1",
      "runId": "uapt-university-of-liverpool-20260514",
      "artifactType": "source_candidate",
      "sourceCandidateId": "sc-liverpool-foundations-copilot",
      "entityType": "university",
      "entitySlug": "university-of-liverpool",
      "sourceUrl": "https://www.liverpool.ac.uk/about/the-university/reports-policies-and-governance/ai-at-liverpool/foundations-of-ai/",
      "finalUrl": "https://www.liverpool.ac.uk/about/the-university/reports-policies-and-governance/ai-at-liverpool/foundations-of-ai/",
      "sourceTitle": "Foundations of AI",
      "sourceLanguage": "en",
      "sourceType": "approved_tools",
      "discoveryMethod": "public_web_search",
      "queryUsed": "site:liverpool.ac.uk University of Liverpool AI data protection security Microsoft Copilot generative AI policies guidance",
      "discoveredAt": "2026-05-14T22:24:00.000Z",
      "officialDomainConfidence": 1,
      "aiRelevanceScore": 0.96,
      "policySpecificityScore": 0.88,
      "verificationStatus": "verified",
      "verifiedAt": "2026-05-14T22:48:00.000Z",
      "verificationNotes": "Official University of Liverpool AI page describing Microsoft Copilot as the endorsed generative AI chat tool for University work and explaining enterprise data protection context.",
      "robotsPolicy": "respect"
    },
    {
      "schemaVersion": "openclaw-artifact-v1",
      "runId": "uapt-university-of-liverpool-20260514",
      "artifactType": "source_candidate",
      "sourceCandidateId": "sc-liverpool-golden-rules",
      "entityType": "university",
      "entitySlug": "university-of-liverpool",
      "sourceUrl": "https://www.liverpool.ac.uk/about/the-university/reports-policies-and-governance/ai-at-liverpool/policies-and-guidance/golden-rules/",
      "finalUrl": "https://www.liverpool.ac.uk/about/the-university/reports-policies-and-governance/ai-at-liverpool/policies-and-guidance/golden-rules/",
      "sourceTitle": "Golden rules",
      "sourceLanguage": "en",
      "sourceType": "university_guidance",
      "discoveryMethod": "link_traversal",
      "queryUsed": "official AI policies and guidance hub link",
      "discoveredAt": "2026-05-14T22:28:00.000Z",
      "officialDomainConfidence": 1,
      "aiRelevanceScore": 0.97,
      "policySpecificityScore": 0.93,
      "verificationStatus": "verified",
      "verifiedAt": "2026-05-14T22:48:00.000Z",
      "verificationNotes": "Official central page listing Golden rules for GenAI use by students and staff.",
      "robotsPolicy": "respect"
    },
    {
      "schemaVersion": "openclaw-artifact-v1",
      "runId": "uapt-university-of-liverpool-20260514",
      "artifactType": "source_candidate",
      "sourceCandidateId": "sc-liverpool-research-guidance",
      "entityType": "university",
      "entitySlug": "university-of-liverpool",
      "sourceUrl": "https://www.liverpool.ac.uk/about/the-university/reports-policies-and-governance/ai-at-liverpool/policies-and-guidance/guidance-for-research/",
      "finalUrl": "https://www.liverpool.ac.uk/about/the-university/reports-policies-and-governance/ai-at-liverpool/policies-and-guidance/guidance-for-research/",
      "sourceTitle": "University guidance on generative artificial intelligence for research",
      "sourceLanguage": "en",
      "sourceType": "research_guidance",
      "discoveryMethod": "link_traversal",
      "queryUsed": "official AI policies and guidance hub link",
      "discoveredAt": "2026-05-14T22:29:00.000Z",
      "officialDomainConfidence": 1,
      "aiRelevanceScore": 0.98,
      "policySpecificityScore": 0.94,
      "verificationStatus": "verified",
      "verifiedAt": "2026-05-14T22:48:00.000Z",
      "verificationNotes": "Official central research guidance page describing responsible and inappropriate GenAI use across the research lifecycle.",
      "robotsPolicy": "respect"
    },
    {
      "schemaVersion": "openclaw-artifact-v1",
      "runId": "uapt-university-of-liverpool-20260514",
      "artifactType": "source_candidate",
      "sourceCandidateId": "sc-liverpool-news-academic-integrity",
      "entityType": "university",
      "entitySlug": "university-of-liverpool",
      "sourceUrl": "https://news.liverpool.ac.uk/2023/04/26/the-importance-of-academic-integrity-ai-and-essay-mills/",
      "finalUrl": "https://news.liverpool.ac.uk/2023/04/26/the-importance-of-academic-integrity-ai-and-essay-mills/",
      "sourceTitle": "The importance of academic integrity: AI and essay mills",
      "sourceLanguage": "en",
      "sourceType": "official_news_advisory",
      "discoveryMethod": "public_web_search",
      "queryUsed": "site:liverpool.ac.uk University of Liverpool generative AI policy students assessment academic integrity artificial intelligence",
      "discoveredAt": "2026-05-14T22:21:00.000Z",
      "officialDomainConfidence": 1,
      "aiRelevanceScore": 0.9,
      "policySpecificityScore": 0.78,
      "verificationStatus": "rejected",
      "verifiedAt": "2026-05-14T22:48:00.000Z",
      "verificationNotes": "Official student news item from 2023 was fetched, but current central AI policy pages provide better authority for staged claims.",
      "rejectionReason": "event_or_news_only",
      "robotsPolicy": "respect"
    },
    {
      "schemaVersion": "openclaw-artifact-v1",
      "runId": "uapt-university-of-liverpool-20260514",
      "artifactType": "source_candidate",
      "sourceCandidateId": "sc-liverpool-repository-genai-assessment-poster",
      "entityType": "university",
      "entitySlug": "university-of-liverpool",
      "sourceUrl": "https://livrepository.liverpool.ac.uk/3193704/1/Safeguarding%20Assessments%20in%20Higher%20Education%20Institutions%20in%20the%20UK%20from%20Student%20Misuse%20of%20Generative%20Artificial%20Intelligence%20%28GenAI%29.pdf",
      "finalUrl": "https://livrepository.liverpool.ac.uk/3193704/1/Safeguarding%20Assessments%20in%20Higher%20Education%20Institutions%20in%20the%20UK%20from%20Student%20Misuse%20of%20Generative%20Artificial%20Intelligence%20%28GenAI%29.pdf",
      "sourceTitle": "Safeguarding Assessments in Higher Education Institutions in the UK from Student Misuse of Generative Artificial Intelligence",
      "sourceLanguage": "en",
      "sourceType": "research_showcase",
      "discoveryMethod": "public_web_search",
      "queryUsed": "site:liverpool.ac.uk University of Liverpool generative AI policy students assessment academic integrity artificial intelligence",
      "discoveredAt": "2026-05-14T22:21:00.000Z",
      "officialDomainConfidence": 0.92,
      "aiRelevanceScore": 0.88,
      "policySpecificityScore": 0.62,
      "verificationStatus": "rejected",
      "verifiedAt": "2026-05-14T22:48:00.000Z",
      "verificationNotes": "Repository PDF is a research poster/case-study source, not a central University policy or guidance page.",
      "rejectionReason": "research_showcase_only",
      "robotsPolicy": "respect"
    },
    {
      "schemaVersion": "openclaw-artifact-v1",
      "runId": "uapt-university-of-liverpool-20260514",
      "artifactType": "source_rejection",
      "sourceRejectionId": "sr-liverpool-news-academic-integrity",
      "sourceCandidateId": "sc-liverpool-news-academic-integrity",
      "entityType": "university",
      "entitySlug": "university-of-liverpool",
      "sourceUrl": "https://news.liverpool.ac.uk/2023/04/26/the-importance-of-academic-integrity-ai-and-essay-mills/",
      "finalUrl": "https://news.liverpool.ac.uk/2023/04/26/the-importance-of-academic-integrity-ai-and-essay-mills/",
      "rejectedAt": "2026-05-14T22:48:00.000Z",
      "rejectionReason": "event_or_news_only",
      "checkedBy": "openclaw-agent",
      "evidenceSnippet": "Overall, it is safest to assume that the use of Generative AI tools for assessment is prohibited, unless you are specifically informed otherwise.",
      "notes": "Fetched and reviewed as official University news, but excluded from current staged claims because the central AI at Liverpool policy pages are newer, broader, and more authoritative."
    },
    {
      "schemaVersion": "openclaw-artifact-v1",
      "runId": "uapt-university-of-liverpool-20260514",
      "artifactType": "source_rejection",
      "sourceRejectionId": "sr-liverpool-repository-genai-assessment-poster",
      "sourceCandidateId": "sc-liverpool-repository-genai-assessment-poster",
      "entityType": "university",
      "entitySlug": "university-of-liverpool",
      "sourceUrl": "https://livrepository.liverpool.ac.uk/3193704/1/Safeguarding%20Assessments%20in%20Higher%20Education%20Institutions%20in%20the%20UK%20from%20Student%20Misuse%20of%20Generative%20Artificial%20Intelligence%20%28GenAI%29.pdf",
      "finalUrl": "https://livrepository.liverpool.ac.uk/3193704/1/Safeguarding%20Assessments%20in%20Higher%20Education%20Institutions%20in%20the%20UK%20from%20Student%20Misuse%20of%20Generative%20Artificial%20Intelligence%20%28GenAI%29.pdf",
      "rejectedAt": "2026-05-14T22:48:00.000Z",
      "rejectionReason": "research_showcase_only",
      "checkedBy": "openclaw-agent",
      "evidenceSnippet": "This project will use a case study research design focusing on the School of Law and Social Justice and the Management School at the University of Liverpool.",
      "notes": "Fetched and reviewed, but rejected because it is a repository research poster and unit/case-study material rather than central University policy evidence."
    },
    {
      "schemaVersion": "openclaw-artifact-v1",
      "runId": "uapt-university-of-liverpool-20260514",
      "artifactType": "fetch_attempt",
      "fetchAttemptId": "fa-liverpool-ai-policies-hub",
      "sourceCandidateId": "sc-liverpool-ai-policies-hub",
      "sourceUrl": "https://www.liverpool.ac.uk/about/the-university/reports-policies-and-governance/ai-at-liverpool/policies-and-guidance/",
      "finalUrl": "https://www.liverpool.ac.uk/about/the-university/reports-policies-and-governance/ai-at-liverpool/policies-and-guidance/",
      "attemptedAt": "2026-05-14T22:35:00.000Z",
      "fetchMode": "firecrawl",
      "userAgentKind": "firecrawl",
      "httpStatus": 200,
      "contentType": "text/html; charset=UTF-8",
      "robotsAllowed": true,
      "outcome": "success",
      "durationMs": 401,
      "contentHash": "c498e5be49758b95222e2cdc981a1be54d59b9e898b01ba05fc9dcfa94128157",
      "normalizedTextStorageKey": "openclaw/uapt-university-of-liverpool-20260514/snapshots/ss-liverpool-ai-policies-hub.txt"
    },
    {
      "schemaVersion": "openclaw-artifact-v1",
      "runId": "uapt-university-of-liverpool-20260514",
      "artifactType": "fetch_attempt",
      "fetchAttemptId": "fa-liverpool-genai-lta-guidance",
      "sourceCandidateId": "sc-liverpool-genai-lta-guidance",
      "sourceUrl": "https://www.liverpool.ac.uk/about/the-university/reports-policies-and-governance/ai-at-liverpool/policies-and-guidance/guidance-learning-teaching-and-assessment/",
      "finalUrl": "https://www.liverpool.ac.uk/about/the-university/reports-policies-and-governance/ai-at-liverpool/policies-and-guidance/guidance-learning-teaching-and-assessment/",
      "attemptedAt": "2026-05-14T22:35:00.000Z",
      "fetchMode": "firecrawl",
      "userAgentKind": "firecrawl",
      "httpStatus": 200,
      "contentType": "text/html; charset=UTF-8",
      "robotsAllowed": true,
      "outcome": "success",
      "durationMs": 414,
      "contentHash": "e5d1080409e9a0c1f7890626167ffd70b8a49fbf0d5316e57ab2689b586f43e6",
      "normalizedTextStorageKey": "openclaw/uapt-university-of-liverpool-20260514/snapshots/ss-liverpool-genai-lta-guidance.txt"
    },
    {
      "schemaVersion": "openclaw-artifact-v1",
      "runId": "uapt-university-of-liverpool-20260514",
      "artifactType": "fetch_attempt",
      "fetchAttemptId": "fa-liverpool-legal-security-data",
      "sourceCandidateId": "sc-liverpool-legal-security-data",
      "sourceUrl": "https://www.liverpool.ac.uk/about/the-university/reports-policies-and-governance/ai-at-liverpool/policies-and-guidance/legal-security-and-data-protection/",
      "finalUrl": "https://www.liverpool.ac.uk/about/the-university/reports-policies-and-governance/ai-at-liverpool/policies-and-guidance/legal-security-and-data-protection/",
      "attemptedAt": "2026-05-14T22:35:00.000Z",
      "fetchMode": "firecrawl",
      "userAgentKind": "firecrawl",
      "httpStatus": 200,
      "contentType": "text/html; charset=UTF-8",
      "robotsAllowed": true,
      "outcome": "success",
      "durationMs": 309,
      "contentHash": "e8d63788f7f7c96b4d66f9f78a0834d016523810c734a7fad3a197e9594495e6",
      "normalizedTextStorageKey": "openclaw/uapt-university-of-liverpool-20260514/snapshots/ss-liverpool-legal-security-data.txt"
    },
    {
      "schemaVersion": "openclaw-artifact-v1",
      "runId": "uapt-university-of-liverpool-20260514",
      "artifactType": "fetch_attempt",
      "fetchAttemptId": "fa-liverpool-foundations-copilot",
      "sourceCandidateId": "sc-liverpool-foundations-copilot",
      "sourceUrl": "https://www.liverpool.ac.uk/about/the-university/reports-policies-and-governance/ai-at-liverpool/foundations-of-ai/",
      "finalUrl": "https://www.liverpool.ac.uk/about/the-university/reports-policies-and-governance/ai-at-liverpool/foundations-of-ai/",
      "attemptedAt": "2026-05-14T22:35:00.000Z",
      "fetchMode": "firecrawl",
      "userAgentKind": "firecrawl",
      "httpStatus": 200,
      "contentType": "text/html; charset=UTF-8",
      "robotsAllowed": true,
      "outcome": "success",
      "durationMs": 260,
      "contentHash": "ebc4570e49fdb8a336414fde220f1646a96f222e9d0591c3d5b05f2ecef5c38e",
      "normalizedTextStorageKey": "openclaw/uapt-university-of-liverpool-20260514/snapshots/ss-liverpool-foundations-copilot.txt"
    },
    {
      "schemaVersion": "openclaw-artifact-v1",
      "runId": "uapt-university-of-liverpool-20260514",
      "artifactType": "fetch_attempt",
      "fetchAttemptId": "fa-liverpool-golden-rules",
      "sourceCandidateId": "sc-liverpool-golden-rules",
      "sourceUrl": "https://www.liverpool.ac.uk/about/the-university/reports-policies-and-governance/ai-at-liverpool/policies-and-guidance/golden-rules/",
      "finalUrl": "https://www.liverpool.ac.uk/about/the-university/reports-policies-and-governance/ai-at-liverpool/policies-and-guidance/golden-rules/",
      "attemptedAt": "2026-05-14T22:38:00.000Z",
      "fetchMode": "firecrawl",
      "userAgentKind": "firecrawl",
      "httpStatus": 200,
      "contentType": "text/html; charset=UTF-8",
      "robotsAllowed": true,
      "outcome": "success",
      "durationMs": 403,
      "contentHash": "30ce6807f5aa50541739241017dab9f1e41d1256e0f48c2b91fa51882ee116d4",
      "normalizedTextStorageKey": "openclaw/uapt-university-of-liverpool-20260514/snapshots/ss-liverpool-golden-rules.txt"
    },
    {
      "schemaVersion": "openclaw-artifact-v1",
      "runId": "uapt-university-of-liverpool-20260514",
      "artifactType": "fetch_attempt",
      "fetchAttemptId": "fa-liverpool-research-guidance",
      "sourceCandidateId": "sc-liverpool-research-guidance",
      "sourceUrl": "https://www.liverpool.ac.uk/about/the-university/reports-policies-and-governance/ai-at-liverpool/policies-and-guidance/guidance-for-research/",
      "finalUrl": "https://www.liverpool.ac.uk/about/the-university/reports-policies-and-governance/ai-at-liverpool/policies-and-guidance/guidance-for-research/",
      "attemptedAt": "2026-05-14T22:39:00.000Z",
      "fetchMode": "firecrawl",
      "userAgentKind": "firecrawl",
      "httpStatus": 200,
      "contentType": "text/html; charset=UTF-8",
      "robotsAllowed": true,
      "outcome": "success",
      "durationMs": 356,
      "contentHash": "dc99c7a5a316610f03570aa8a1202e89bf47477c24f1738cdffa344baf622835",
      "normalizedTextStorageKey": "openclaw/uapt-university-of-liverpool-20260514/snapshots/ss-liverpool-research-guidance.txt"
    },
    {
      "schemaVersion": "openclaw-artifact-v1",
      "runId": "uapt-university-of-liverpool-20260514",
      "artifactType": "fetch_attempt",
      "fetchAttemptId": "fa-liverpool-news-academic-integrity",
      "sourceCandidateId": "sc-liverpool-news-academic-integrity",
      "sourceUrl": "https://news.liverpool.ac.uk/2023/04/26/the-importance-of-academic-integrity-ai-and-essay-mills/",
      "finalUrl": "https://news.liverpool.ac.uk/2023/04/26/the-importance-of-academic-integrity-ai-and-essay-mills/",
      "attemptedAt": "2026-05-14T22:41:00.000Z",
      "fetchMode": "firecrawl",
      "userAgentKind": "firecrawl",
      "httpStatus": 200,
      "contentType": "text/html; charset=UTF-8",
      "robotsAllowed": true,
      "outcome": "success",
      "durationMs": 6577,
      "contentHash": "350736acfb51faa9c16d6ccb3c6fac98ffe1ee6e1880d0b5183b48f7747bafe5",
      "normalizedTextStorageKey": "openclaw/uapt-university-of-liverpool-20260514/rejected/news-academic-integrity.txt"
    },
    {
      "schemaVersion": "openclaw-artifact-v1",
      "runId": "uapt-university-of-liverpool-20260514",
      "artifactType": "fetch_attempt",
      "fetchAttemptId": "fa-liverpool-repository-genai-assessment-poster",
      "sourceCandidateId": "sc-liverpool-repository-genai-assessment-poster",
      "sourceUrl": "https://livrepository.liverpool.ac.uk/3193704/1/Safeguarding%20Assessments%20in%20Higher%20Education%20Institutions%20in%20the%20UK%20from%20Student%20Misuse%20of%20Generative%20Artificial%20Intelligence%20%28GenAI%29.pdf",
      "finalUrl": "https://livrepository.liverpool.ac.uk/3193704/1/Safeguarding%20Assessments%20in%20Higher%20Education%20Institutions%20in%20the%20UK%20from%20Student%20Misuse%20of%20Generative%20Artificial%20Intelligence%20%28GenAI%29.pdf",
      "attemptedAt": "2026-05-14T22:41:00.000Z",
      "fetchMode": "firecrawl",
      "userAgentKind": "firecrawl",
      "httpStatus": 200,
      "contentType": "application/pdf",
      "robotsAllowed": true,
      "outcome": "success",
      "durationMs": 2982,
      "contentHash": "aa254fc00b88c0652b8c0c7f73cec1777be04f16218a47dbca72c017e496cf27",
      "normalizedTextStorageKey": "openclaw/uapt-university-of-liverpool-20260514/rejected/repository-genai-assessment-poster.txt"
    },
    {
      "schemaVersion": "openclaw-artifact-v1",
      "runId": "uapt-university-of-liverpool-20260514",
      "artifactType": "source_snapshot",
      "sourceSnapshotId": "ss-liverpool-ai-policies-hub",
      "sourceCandidateId": "sc-liverpool-ai-policies-hub",
      "fetchAttemptId": "fa-liverpool-ai-policies-hub",
      "sourceUrl": "https://www.liverpool.ac.uk/about/the-university/reports-policies-and-governance/ai-at-liverpool/policies-and-guidance/",
      "finalUrl": "https://www.liverpool.ac.uk/about/the-university/reports-policies-and-governance/ai-at-liverpool/policies-and-guidance/",
      "sourceTitle": "University of Liverpool policies and guidance on AI",
      "sourceLanguage": "en",
      "contentHash": "c498e5be49758b95222e2cdc981a1be54d59b9e898b01ba05fc9dcfa94128157",
      "fetchedAt": "2026-05-14T22:35:00.000Z",
      "httpStatus": 200,
      "robotsAllowed": true,
      "normalizedTextStorageKey": "openclaw/uapt-university-of-liverpool-20260514/snapshots/ss-liverpool-ai-policies-hub.txt",
      "rawArtifactPaths": []
    },
    {
      "schemaVersion": "openclaw-artifact-v1",
      "runId": "uapt-university-of-liverpool-20260514",
      "artifactType": "source_snapshot",
      "sourceSnapshotId": "ss-liverpool-genai-lta-guidance",
      "sourceCandidateId": "sc-liverpool-genai-lta-guidance",
      "fetchAttemptId": "fa-liverpool-genai-lta-guidance",
      "sourceUrl": "https://www.liverpool.ac.uk/about/the-university/reports-policies-and-governance/ai-at-liverpool/policies-and-guidance/guidance-learning-teaching-and-assessment/",
      "finalUrl": "https://www.liverpool.ac.uk/about/the-university/reports-policies-and-governance/ai-at-liverpool/policies-and-guidance/guidance-learning-teaching-and-assessment/",
      "sourceTitle": "University guidance on GenAI in learning, teaching and assessment",
      "sourceLanguage": "en",
      "contentHash": "e5d1080409e9a0c1f7890626167ffd70b8a49fbf0d5316e57ab2689b586f43e6",
      "fetchedAt": "2026-05-14T22:35:00.000Z",
      "httpStatus": 200,
      "robotsAllowed": true,
      "normalizedTextStorageKey": "openclaw/uapt-university-of-liverpool-20260514/snapshots/ss-liverpool-genai-lta-guidance.txt",
      "rawArtifactPaths": []
    },
    {
      "schemaVersion": "openclaw-artifact-v1",
      "runId": "uapt-university-of-liverpool-20260514",
      "artifactType": "source_snapshot",
      "sourceSnapshotId": "ss-liverpool-legal-security-data",
      "sourceCandidateId": "sc-liverpool-legal-security-data",
      "fetchAttemptId": "fa-liverpool-legal-security-data",
      "sourceUrl": "https://www.liverpool.ac.uk/about/the-university/reports-policies-and-governance/ai-at-liverpool/policies-and-guidance/legal-security-and-data-protection/",
      "finalUrl": "https://www.liverpool.ac.uk/about/the-university/reports-policies-and-governance/ai-at-liverpool/policies-and-guidance/legal-security-and-data-protection/",
      "sourceTitle": "Legal, security and data protection",
      "sourceLanguage": "en",
      "contentHash": "e8d63788f7f7c96b4d66f9f78a0834d016523810c734a7fad3a197e9594495e6",
      "fetchedAt": "2026-05-14T22:35:00.000Z",
      "httpStatus": 200,
      "robotsAllowed": true,
      "normalizedTextStorageKey": "openclaw/uapt-university-of-liverpool-20260514/snapshots/ss-liverpool-legal-security-data.txt",
      "rawArtifactPaths": []
    },
    {
      "schemaVersion": "openclaw-artifact-v1",
      "runId": "uapt-university-of-liverpool-20260514",
      "artifactType": "source_snapshot",
      "sourceSnapshotId": "ss-liverpool-foundations-copilot",
      "sourceCandidateId": "sc-liverpool-foundations-copilot",
      "fetchAttemptId": "fa-liverpool-foundations-copilot",
      "sourceUrl": "https://www.liverpool.ac.uk/about/the-university/reports-policies-and-governance/ai-at-liverpool/foundations-of-ai/",
      "finalUrl": "https://www.liverpool.ac.uk/about/the-university/reports-policies-and-governance/ai-at-liverpool/foundations-of-ai/",
      "sourceTitle": "Foundations of AI",
      "sourceLanguage": "en",
      "contentHash": "ebc4570e49fdb8a336414fde220f1646a96f222e9d0591c3d5b05f2ecef5c38e",
      "fetchedAt": "2026-05-14T22:35:00.000Z",
      "httpStatus": 200,
      "robotsAllowed": true,
      "normalizedTextStorageKey": "openclaw/uapt-university-of-liverpool-20260514/snapshots/ss-liverpool-foundations-copilot.txt",
      "rawArtifactPaths": []
    },
    {
      "schemaVersion": "openclaw-artifact-v1",
      "runId": "uapt-university-of-liverpool-20260514",
      "artifactType": "source_snapshot",
      "sourceSnapshotId": "ss-liverpool-golden-rules",
      "sourceCandidateId": "sc-liverpool-golden-rules",
      "fetchAttemptId": "fa-liverpool-golden-rules",
      "sourceUrl": "https://www.liverpool.ac.uk/about/the-university/reports-policies-and-governance/ai-at-liverpool/policies-and-guidance/golden-rules/",
      "finalUrl": "https://www.liverpool.ac.uk/about/the-university/reports-policies-and-governance/ai-at-liverpool/policies-and-guidance/golden-rules/",
      "sourceTitle": "Golden rules",
      "sourceLanguage": "en",
      "contentHash": "30ce6807f5aa50541739241017dab9f1e41d1256e0f48c2b91fa51882ee116d4",
      "fetchedAt": "2026-05-14T22:38:00.000Z",
      "httpStatus": 200,
      "robotsAllowed": true,
      "normalizedTextStorageKey": "openclaw/uapt-university-of-liverpool-20260514/snapshots/ss-liverpool-golden-rules.txt",
      "rawArtifactPaths": []
    },
    {
      "schemaVersion": "openclaw-artifact-v1",
      "runId": "uapt-university-of-liverpool-20260514",
      "artifactType": "source_snapshot",
      "sourceSnapshotId": "ss-liverpool-research-guidance",
      "sourceCandidateId": "sc-liverpool-research-guidance",
      "fetchAttemptId": "fa-liverpool-research-guidance",
      "sourceUrl": "https://www.liverpool.ac.uk/about/the-university/reports-policies-and-governance/ai-at-liverpool/policies-and-guidance/guidance-for-research/",
      "finalUrl": "https://www.liverpool.ac.uk/about/the-university/reports-policies-and-governance/ai-at-liverpool/policies-and-guidance/guidance-for-research/",
      "sourceTitle": "University guidance on generative artificial intelligence for research",
      "sourceLanguage": "en",
      "contentHash": "dc99c7a5a316610f03570aa8a1202e89bf47477c24f1738cdffa344baf622835",
      "fetchedAt": "2026-05-14T22:39:00.000Z",
      "httpStatus": 200,
      "robotsAllowed": true,
      "normalizedTextStorageKey": "openclaw/uapt-university-of-liverpool-20260514/snapshots/ss-liverpool-research-guidance.txt",
      "rawArtifactPaths": []
    },
    {
      "schemaVersion": "openclaw-artifact-v1",
      "runId": "uapt-university-of-liverpool-20260514",
      "artifactType": "claim_candidate",
      "claimId": "claim-liverpool-ai-guidance-hub",
      "entityType": "university",
      "entitySlug": "university-of-liverpool",
      "claimType": "source_status",
      "claimText": "The University of Liverpool has a central AI policies and guidance hub that collates generative AI guidance covering golden rules, legal/security/data protection, learning/teaching/assessment, and research.",
      "normalizedValue": "central_ai_guidance_hub",
      "sourceLanguage": "en",
      "confidence": 0.94,
      "reviewState": "agent_reviewed",
      "evidenceIds": [
        "ev-liverpool-ai-guidance-hub"
      ],
      "citation": {
        "citationTitle": "University of Liverpool policies and guidance on AI",
        "sourceUrl": "https://www.liverpool.ac.uk/about/the-university/reports-policies-and-governance/ai-at-liverpool/policies-and-guidance/",
        "publicJsonUrl": "https://eduaipolicy.org/api/public/v1/claims/university-of-liverpool.json",
        "canonicalUrl": "https://eduaipolicy.org/universities/university-of-liverpool",
        "publisher": "University of Liverpool",
        "retrievedAt": "2026-05-14T22:35:00.000Z",
        "snapshotHash": "c498e5be49758b95222e2cdc981a1be54d59b9e898b01ba05fc9dcfa94128157",
        "sourceRights": "Tracker metadata is open licensed. Official source documents, page text, PDFs, and other source materials retain their original rights and terms."
      },
      "publishAsCanonical": false,
      "isCanonical": false
    },
    {
      "schemaVersion": "openclaw-artifact-v1",
      "runId": "uapt-university-of-liverpool-20260514",
      "artifactType": "claim_candidate",
      "claimId": "claim-liverpool-genai-lta-position",
      "entityType": "university",
      "entitySlug": "university-of-liverpool",
      "claimType": "teaching",
      "claimText": "Liverpool's central GenAI learning, teaching, and assessment page says the University has devised guidance to help academics and students understand its position and make informed decisions on when and how to use GenAI.",
      "normalizedValue": "central_lta_guidance_for_academics_and_students",
      "sourceLanguage": "en",
      "confidence": 0.94,
      "reviewState": "agent_reviewed",
      "evidenceIds": [
        "ev-liverpool-genai-lta-position"
      ],
      "citation": {
        "citationTitle": "University guidance on GenAI in learning, teaching and assessment",
        "sourceUrl": "https://www.liverpool.ac.uk/about/the-university/reports-policies-and-governance/ai-at-liverpool/policies-and-guidance/guidance-learning-teaching-and-assessment/",
        "publicJsonUrl": "https://eduaipolicy.org/api/public/v1/claims/university-of-liverpool.json",
        "canonicalUrl": "https://eduaipolicy.org/universities/university-of-liverpool",
        "publisher": "University of Liverpool",
        "retrievedAt": "2026-05-14T22:35:00.000Z",
        "snapshotHash": "e5d1080409e9a0c1f7890626167ffd70b8a49fbf0d5316e57ab2689b586f43e6",
        "sourceRights": "Tracker metadata is open licensed. Official source documents, page text, PDFs, and other source materials retain their original rights and terms."
      },
      "publishAsCanonical": false,
      "isCanonical": false
    },
    {
      "schemaVersion": "openclaw-artifact-v1",
      "runId": "uapt-university-of-liverpool-20260514",
      "artifactType": "claim_candidate",
      "claimId": "claim-liverpool-education-unacceptable-uses",
      "entityType": "university",
      "entitySlug": "university-of-liverpool",
      "claimType": "academic_integrity",
      "claimText": "Liverpool lists unacceptable uses of generative AI in education, including unreviewed copying of AI-generated content into assessment materials or feedback, using AI for grades or final assessment decisions, uploading protected student or confidential information to public AI platforms without required review, and creating or modifying official policy documents without appropriate review and approval.",
      "normalizedValue": "unacceptable_genai_education_uses_listed",
      "sourceLanguage": "en",
      "confidence": 0.95,
      "reviewState": "agent_reviewed",
      "evidenceIds": [
        "ev-liverpool-education-unacceptable-uses"
      ],
      "citation": {
        "citationTitle": "University guidance on GenAI in learning, teaching and assessment",
        "sourceUrl": "https://www.liverpool.ac.uk/about/the-university/reports-policies-and-governance/ai-at-liverpool/policies-and-guidance/guidance-learning-teaching-and-assessment/",
        "publicJsonUrl": "https://eduaipolicy.org/api/public/v1/claims/university-of-liverpool.json",
        "canonicalUrl": "https://eduaipolicy.org/universities/university-of-liverpool",
        "publisher": "University of Liverpool",
        "retrievedAt": "2026-05-14T22:35:00.000Z",
        "snapshotHash": "e5d1080409e9a0c1f7890626167ffd70b8a49fbf0d5316e57ab2689b586f43e6",
        "sourceRights": "Tracker metadata is open licensed. Official source documents, page text, PDFs, and other source materials retain their original rights and terms."
      },
      "publishAsCanonical": false,
      "isCanonical": false
    },
    {
      "schemaVersion": "openclaw-artifact-v1",
      "runId": "uapt-university-of-liverpool-20260514",
      "artifactType": "claim_candidate",
      "claimId": "claim-liverpool-data-protection-genai",
      "entityType": "university",
      "entitySlug": "university-of-liverpool",
      "claimType": "privacy",
      "claimText": "Liverpool's legal, security, and data-protection guidance says GenAI use must comply with UK GDPR and that personal information should not be uploaded or shared with AI tools unless necessary and appropriate safeguards are in place.",
      "normalizedValue": "genai_personal_data_gdpr_safeguards_required",
      "sourceLanguage": "en",
      "confidence": 0.95,
      "reviewState": "agent_reviewed",
      "evidenceIds": [
        "ev-liverpool-data-protection-genai"
      ],
      "citation": {
        "citationTitle": "Legal, security and data protection",
        "sourceUrl": "https://www.liverpool.ac.uk/about/the-university/reports-policies-and-governance/ai-at-liverpool/policies-and-guidance/legal-security-and-data-protection/",
        "publicJsonUrl": "https://eduaipolicy.org/api/public/v1/claims/university-of-liverpool.json",
        "canonicalUrl": "https://eduaipolicy.org/universities/university-of-liverpool",
        "publisher": "University of Liverpool",
        "retrievedAt": "2026-05-14T22:35:00.000Z",
        "snapshotHash": "e8d63788f7f7c96b4d66f9f78a0834d016523810c734a7fad3a197e9594495e6",
        "sourceRights": "Tracker metadata is open licensed. Official source documents, page text, PDFs, and other source materials retain their original rights and terms."
      },
      "publishAsCanonical": false,
      "isCanonical": false
    },
    {
      "schemaVersion": "openclaw-artifact-v1",
      "runId": "uapt-university-of-liverpool-20260514",
      "artifactType": "claim_candidate",
      "claimId": "claim-liverpool-copilot-endorsed-tool",
      "entityType": "university",
      "entitySlug": "university-of-liverpool",
      "claimType": "ai_tool_treatment",
      "claimText": "For University work, Liverpool says staff and students should use Microsoft Copilot as the endorsed generative AI chat tool, provided through the University's Microsoft 365 environment with data governance and safeguards aligned to institutional requirements.",
      "normalizedValue": "microsoft_copilot_endorsed_genai_chat_tool",
      "sourceLanguage": "en",
      "confidence": 0.94,
      "reviewState": "agent_reviewed",
      "evidenceIds": [
        "ev-liverpool-copilot-endorsed-tool"
      ],
      "citation": {
        "citationTitle": "Foundations of AI",
        "sourceUrl": "https://www.liverpool.ac.uk/about/the-university/reports-policies-and-governance/ai-at-liverpool/foundations-of-ai/",
        "publicJsonUrl": "https://eduaipolicy.org/api/public/v1/claims/university-of-liverpool.json",
        "canonicalUrl": "https://eduaipolicy.org/universities/university-of-liverpool",
        "publisher": "University of Liverpool",
        "retrievedAt": "2026-05-14T22:35:00.000Z",
        "snapshotHash": "ebc4570e49fdb8a336414fde220f1646a96f222e9d0591c3d5b05f2ecef5c38e",
        "sourceRights": "Tracker metadata is open licensed. Official source documents, page text, PDFs, and other source materials retain their original rights and terms."
      },
      "publishAsCanonical": false,
      "isCanonical": false
    },
    {
      "schemaVersion": "openclaw-artifact-v1",
      "runId": "uapt-university-of-liverpool-20260514",
      "artifactType": "claim_candidate",
      "claimId": "claim-liverpool-golden-rules",
      "entityType": "university",
      "entitySlug": "university-of-liverpool",
      "claimType": "other",
      "claimText": "Liverpool's golden rules frame GenAI as a support tool rather than a substitute, and include expectations to acknowledge AI use where required, protect personal and sensitive data, and verify facts.",
      "normalizedValue": "golden_rules_support_attribution_data_accuracy",
      "sourceLanguage": "en",
      "confidence": 0.93,
      "reviewState": "agent_reviewed",
      "evidenceIds": [
        "ev-liverpool-golden-rules"
      ],
      "citation": {
        "citationTitle": "Golden rules",
        "sourceUrl": "https://www.liverpool.ac.uk/about/the-university/reports-policies-and-governance/ai-at-liverpool/policies-and-guidance/golden-rules/",
        "publicJsonUrl": "https://eduaipolicy.org/api/public/v1/claims/university-of-liverpool.json",
        "canonicalUrl": "https://eduaipolicy.org/universities/university-of-liverpool",
        "publisher": "University of Liverpool",
        "retrievedAt": "2026-05-14T22:38:00.000Z",
        "snapshotHash": "30ce6807f5aa50541739241017dab9f1e41d1256e0f48c2b91fa51882ee116d4",
        "sourceRights": "Tracker metadata is open licensed. Official source documents, page text, PDFs, and other source materials retain their original rights and terms."
      },
      "publishAsCanonical": false,
      "isCanonical": false
    },
    {
      "schemaVersion": "openclaw-artifact-v1",
      "runId": "uapt-university-of-liverpool-20260514",
      "artifactType": "claim_candidate",
      "claimId": "claim-liverpool-research-guidance-accountability",
      "entityType": "university",
      "entitySlug": "university-of-liverpool",
      "claimType": "research",
      "claimText": "Liverpool's research guidance says the University supports responsible and ethical GAI use in research, while expecting researchers and professional services colleagues to apply critical judgement, maintain transparency, prioritize integrity, and remain accountable for research outputs and related materials.",
      "normalizedValue": "responsible_research_use_transparency_accountability",
      "sourceLanguage": "en",
      "confidence": 0.94,
      "reviewState": "agent_reviewed",
      "evidenceIds": [
        "ev-liverpool-research-guidance-accountability"
      ],
      "citation": {
        "citationTitle": "University guidance on generative artificial intelligence for research",
        "sourceUrl": "https://www.liverpool.ac.uk/about/the-university/reports-policies-and-governance/ai-at-liverpool/policies-and-guidance/guidance-for-research/",
        "publicJsonUrl": "https://eduaipolicy.org/api/public/v1/claims/university-of-liverpool.json",
        "canonicalUrl": "https://eduaipolicy.org/universities/university-of-liverpool",
        "publisher": "University of Liverpool",
        "retrievedAt": "2026-05-14T22:39:00.000Z",
        "snapshotHash": "dc99c7a5a316610f03570aa8a1202e89bf47477c24f1738cdffa344baf622835",
        "sourceRights": "Tracker metadata is open licensed. Official source documents, page text, PDFs, and other source materials retain their original rights and terms."
      },
      "publishAsCanonical": false,
      "isCanonical": false
    },
    {
      "schemaVersion": "openclaw-artifact-v1",
      "runId": "uapt-university-of-liverpool-20260514",
      "artifactType": "evidence_candidate",
      "evidenceId": "ev-liverpool-ai-guidance-hub",
      "claimId": "claim-liverpool-ai-guidance-hub",
      "sourceSnapshotId": "ss-liverpool-ai-policies-hub",
      "sourceUrl": "https://www.liverpool.ac.uk/about/the-university/reports-policies-and-governance/ai-at-liverpool/policies-and-guidance/",
      "finalUrl": "https://www.liverpool.ac.uk/about/the-university/reports-policies-and-governance/ai-at-liverpool/policies-and-guidance/",
      "sourceTitle": "University of Liverpool policies and guidance on AI",
      "sourceLanguage": "en",
      "snapshotHash": "c498e5be49758b95222e2cdc981a1be54d59b9e898b01ba05fc9dcfa94128157",
      "evidenceSnippetOriginal": "On this page, we have collated our University guidance on generative AI including golden rules, legal, security and data protection, as well as existing guidance on using AI in learning, teaching and assessment, and finally, guidance on generative AI for research.",
      "evidenceLocator": "Page introduction",
      "evidenceType": "official_source",
      "relevance": 0.96,
      "rightsNote": "Tracker metadata is open licensed. Official source documents, page text, PDFs, and other source materials retain their original rights and terms.",
      "citation": {
        "citationTitle": "University of Liverpool policies and guidance on AI",
        "sourceUrl": "https://www.liverpool.ac.uk/about/the-university/reports-policies-and-governance/ai-at-liverpool/policies-and-guidance/",
        "publisher": "University of Liverpool",
        "retrievedAt": "2026-05-14T22:35:00.000Z",
        "snapshotHash": "c498e5be49758b95222e2cdc981a1be54d59b9e898b01ba05fc9dcfa94128157",
        "sourceRights": "Tracker metadata is open licensed. Official source documents, page text, PDFs, and other source materials retain their original rights and terms."
      }
    },
    {
      "schemaVersion": "openclaw-artifact-v1",
      "runId": "uapt-university-of-liverpool-20260514",
      "artifactType": "evidence_candidate",
      "evidenceId": "ev-liverpool-genai-lta-position",
      "claimId": "claim-liverpool-genai-lta-position",
      "sourceSnapshotId": "ss-liverpool-genai-lta-guidance",
      "sourceUrl": "https://www.liverpool.ac.uk/about/the-university/reports-policies-and-governance/ai-at-liverpool/policies-and-guidance/guidance-learning-teaching-and-assessment/",
      "finalUrl": "https://www.liverpool.ac.uk/about/the-university/reports-policies-and-governance/ai-at-liverpool/policies-and-guidance/guidance-learning-teaching-and-assessment/",
      "sourceTitle": "University guidance on GenAI in learning, teaching and assessment",
      "sourceLanguage": "en",
      "snapshotHash": "e5d1080409e9a0c1f7890626167ffd70b8a49fbf0d5316e57ab2689b586f43e6",
      "evidenceSnippetOriginal": "The University of Liverpool has devised guidance to help both academics and students understand the University’s position on GenAI in teaching, learning and assessment, and to make informed decisions on when and how to use it.",
      "evidenceLocator": "Page introduction",
      "evidenceType": "official_source",
      "relevance": 0.96,
      "rightsNote": "Tracker metadata is open licensed. Official source documents, page text, PDFs, and other source materials retain their original rights and terms.",
      "citation": {
        "citationTitle": "University guidance on GenAI in learning, teaching and assessment",
        "sourceUrl": "https://www.liverpool.ac.uk/about/the-university/reports-policies-and-governance/ai-at-liverpool/policies-and-guidance/guidance-learning-teaching-and-assessment/",
        "publisher": "University of Liverpool",
        "retrievedAt": "2026-05-14T22:35:00.000Z",
        "snapshotHash": "e5d1080409e9a0c1f7890626167ffd70b8a49fbf0d5316e57ab2689b586f43e6",
        "sourceRights": "Tracker metadata is open licensed. Official source documents, page text, PDFs, and other source materials retain their original rights and terms."
      }
    },
    {
      "schemaVersion": "openclaw-artifact-v1",
      "runId": "uapt-university-of-liverpool-20260514",
      "artifactType": "evidence_candidate",
      "evidenceId": "ev-liverpool-education-unacceptable-uses",
      "claimId": "claim-liverpool-education-unacceptable-uses",
      "sourceSnapshotId": "ss-liverpool-genai-lta-guidance",
      "sourceUrl": "https://www.liverpool.ac.uk/about/the-university/reports-policies-and-governance/ai-at-liverpool/policies-and-guidance/guidance-learning-teaching-and-assessment/",
      "finalUrl": "https://www.liverpool.ac.uk/about/the-university/reports-policies-and-governance/ai-at-liverpool/policies-and-guidance/guidance-learning-teaching-and-assessment/",
      "sourceTitle": "University guidance on GenAI in learning, teaching and assessment",
      "sourceLanguage": "en",
      "snapshotHash": "e5d1080409e9a0c1f7890626167ffd70b8a49fbf0d5316e57ab2689b586f43e6",
      "evidenceSnippetOriginal": "Unacceptable uses of generative AI in education include copying and pasting AI-generated content directly into assessment briefs, marking rubrics, or feedback without review; using AI to generate grades or make final assessment decisions; uploading student work, personal data, or confidential information to public AI platforms without first completing a Data Protection Impact Assessment.",
      "evidenceLocator": "Unacceptable uses of generative AI in education",
      "evidenceType": "official_source",
      "relevance": 0.97,
      "rightsNote": "Tracker metadata is open licensed. Official source documents, page text, PDFs, and other source materials retain their original rights and terms.",
      "citation": {
        "citationTitle": "University guidance on GenAI in learning, teaching and assessment",
        "sourceUrl": "https://www.liverpool.ac.uk/about/the-university/reports-policies-and-governance/ai-at-liverpool/policies-and-guidance/guidance-learning-teaching-and-assessment/",
        "publisher": "University of Liverpool",
        "retrievedAt": "2026-05-14T22:35:00.000Z",
        "snapshotHash": "e5d1080409e9a0c1f7890626167ffd70b8a49fbf0d5316e57ab2689b586f43e6",
        "sourceRights": "Tracker metadata is open licensed. Official source documents, page text, PDFs, and other source materials retain their original rights and terms."
      }
    },
    {
      "schemaVersion": "openclaw-artifact-v1",
      "runId": "uapt-university-of-liverpool-20260514",
      "artifactType": "evidence_candidate",
      "evidenceId": "ev-liverpool-data-protection-genai",
      "claimId": "claim-liverpool-data-protection-genai",
      "sourceSnapshotId": "ss-liverpool-legal-security-data",
      "sourceUrl": "https://www.liverpool.ac.uk/about/the-university/reports-policies-and-governance/ai-at-liverpool/policies-and-guidance/legal-security-and-data-protection/",
      "finalUrl": "https://www.liverpool.ac.uk/about/the-university/reports-policies-and-governance/ai-at-liverpool/policies-and-guidance/legal-security-and-data-protection/",
      "sourceTitle": "Legal, security and data protection",
      "sourceLanguage": "en",
      "snapshotHash": "e8d63788f7f7c96b4d66f9f78a0834d016523810c734a7fad3a197e9594495e6",
      "evidenceSnippetOriginal": "Any use of generative AI must be compliant with UK General Data Protection Regulations (GDPR). No personal information should be uploaded or shared with any AI tool unless it is necessary, and appropriate safeguarding and protection measures are in place.",
      "evidenceLocator": "Legal, security and data protection guidance",
      "evidenceType": "official_source",
      "relevance": 0.97,
      "rightsNote": "Tracker metadata is open licensed. Official source documents, page text, PDFs, and other source materials retain their original rights and terms.",
      "citation": {
        "citationTitle": "Legal, security and data protection",
        "sourceUrl": "https://www.liverpool.ac.uk/about/the-university/reports-policies-and-governance/ai-at-liverpool/policies-and-guidance/legal-security-and-data-protection/",
        "publisher": "University of Liverpool",
        "retrievedAt": "2026-05-14T22:35:00.000Z",
        "snapshotHash": "e8d63788f7f7c96b4d66f9f78a0834d016523810c734a7fad3a197e9594495e6",
        "sourceRights": "Tracker metadata is open licensed. Official source documents, page text, PDFs, and other source materials retain their original rights and terms."
      }
    },
    {
      "schemaVersion": "openclaw-artifact-v1",
      "runId": "uapt-university-of-liverpool-20260514",
      "artifactType": "evidence_candidate",
      "evidenceId": "ev-liverpool-copilot-endorsed-tool",
      "claimId": "claim-liverpool-copilot-endorsed-tool",
      "sourceSnapshotId": "ss-liverpool-foundations-copilot",
      "sourceUrl": "https://www.liverpool.ac.uk/about/the-university/reports-policies-and-governance/ai-at-liverpool/foundations-of-ai/",
      "finalUrl": "https://www.liverpool.ac.uk/about/the-university/reports-policies-and-governance/ai-at-liverpool/foundations-of-ai/",
      "sourceTitle": "Foundations of AI",
      "sourceLanguage": "en",
      "snapshotHash": "ebc4570e49fdb8a336414fde220f1646a96f222e9d0591c3d5b05f2ecef5c38e",
      "evidenceSnippetOriginal": "For University work, staff and students should use Microsoft Copilot – the endorsed generative AI chat tool. Copilot is provided through the University's Microsoft 365 environment, with data governance and safeguards aligned to our institutional requirements.",
      "evidenceLocator": "Microsoft Copilot section",
      "evidenceType": "official_source",
      "relevance": 0.97,
      "rightsNote": "Tracker metadata is open licensed. Official source documents, page text, PDFs, and other source materials retain their original rights and terms.",
      "citation": {
        "citationTitle": "Foundations of AI",
        "sourceUrl": "https://www.liverpool.ac.uk/about/the-university/reports-policies-and-governance/ai-at-liverpool/foundations-of-ai/",
        "publisher": "University of Liverpool",
        "retrievedAt": "2026-05-14T22:35:00.000Z",
        "snapshotHash": "ebc4570e49fdb8a336414fde220f1646a96f222e9d0591c3d5b05f2ecef5c38e",
        "sourceRights": "Tracker metadata is open licensed. Official source documents, page text, PDFs, and other source materials retain their original rights and terms."
      }
    },
    {
      "schemaVersion": "openclaw-artifact-v1",
      "runId": "uapt-university-of-liverpool-20260514",
      "artifactType": "evidence_candidate",
      "evidenceId": "ev-liverpool-golden-rules",
      "claimId": "claim-liverpool-golden-rules",
      "sourceSnapshotId": "ss-liverpool-golden-rules",
      "sourceUrl": "https://www.liverpool.ac.uk/about/the-university/reports-policies-and-governance/ai-at-liverpool/policies-and-guidance/golden-rules/",
      "finalUrl": "https://www.liverpool.ac.uk/about/the-university/reports-policies-and-governance/ai-at-liverpool/policies-and-guidance/golden-rules/",
      "sourceTitle": "Golden rules",
      "sourceLanguage": "en",
      "snapshotHash": "30ce6807f5aa50541739241017dab9f1e41d1256e0f48c2b91fa51882ee116d4",
      "evidenceSnippetOriginal": "Use AI to support your work, but do not copy-paste outputs into assessed work, research submissions, or official documents without review and attribution. Where required, acknowledge AI use in your work. Include the tool name, version, and date of use for transparency.",
      "evidenceLocator": "Golden rules list",
      "evidenceType": "official_source",
      "relevance": 0.95,
      "rightsNote": "Tracker metadata is open licensed. Official source documents, page text, PDFs, and other source materials retain their original rights and terms.",
      "citation": {
        "citationTitle": "Golden rules",
        "sourceUrl": "https://www.liverpool.ac.uk/about/the-university/reports-policies-and-governance/ai-at-liverpool/policies-and-guidance/golden-rules/",
        "publisher": "University of Liverpool",
        "retrievedAt": "2026-05-14T22:38:00.000Z",
        "snapshotHash": "30ce6807f5aa50541739241017dab9f1e41d1256e0f48c2b91fa51882ee116d4",
        "sourceRights": "Tracker metadata is open licensed. Official source documents, page text, PDFs, and other source materials retain their original rights and terms."
      }
    },
    {
      "schemaVersion": "openclaw-artifact-v1",
      "runId": "uapt-university-of-liverpool-20260514",
      "artifactType": "evidence_candidate",
      "evidenceId": "ev-liverpool-research-guidance-accountability",
      "claimId": "claim-liverpool-research-guidance-accountability",
      "sourceSnapshotId": "ss-liverpool-research-guidance",
      "sourceUrl": "https://www.liverpool.ac.uk/about/the-university/reports-policies-and-governance/ai-at-liverpool/policies-and-guidance/guidance-for-research/",
      "finalUrl": "https://www.liverpool.ac.uk/about/the-university/reports-policies-and-governance/ai-at-liverpool/policies-and-guidance/guidance-for-research/",
      "sourceTitle": "University guidance on generative artificial intelligence for research",
      "sourceLanguage": "en",
      "snapshotHash": "dc99c7a5a316610f03570aa8a1202e89bf47477c24f1738cdffa344baf622835",
      "evidenceSnippetOriginal": "The University expects all researchers and professional services colleagues to apply critical judgement, maintain transparency, and prioritise integrity at all times. Users remain fully accountable for all research outputs, submissions, analyses, and assessment materials - regardless of whether AI tools were used in their preparation.",
      "evidenceLocator": "Research guidance introduction",
      "evidenceType": "official_source",
      "relevance": 0.96,
      "rightsNote": "Tracker metadata is open licensed. Official source documents, page text, PDFs, and other source materials retain their original rights and terms.",
      "citation": {
        "citationTitle": "University guidance on generative artificial intelligence for research",
        "sourceUrl": "https://www.liverpool.ac.uk/about/the-university/reports-policies-and-governance/ai-at-liverpool/policies-and-guidance/guidance-for-research/",
        "publisher": "University of Liverpool",
        "retrievedAt": "2026-05-14T22:39:00.000Z",
        "snapshotHash": "dc99c7a5a316610f03570aa8a1202e89bf47477c24f1738cdffa344baf622835",
        "sourceRights": "Tracker metadata is open licensed. Official source documents, page text, PDFs, and other source materials retain their original rights and terms."
      }
    },
    {
      "schemaVersion": "openclaw-artifact-v1",
      "runId": "uapt-university-of-liverpool-20260514",
      "artifactType": "review_decision",
      "decisionId": "rd-liverpool-ai-guidance-hub",
      "claimId": "claim-liverpool-ai-guidance-hub",
      "decision": "approve",
      "reviewState": "agent_reviewed",
      "reviewerType": "openclaw_agent",
      "reviewer": "codex-openclaw-staged-crawl",
      "notes": "Approved as a source-status claim because the evidence is the official central AI policies and guidance hub and does not overstate the linked content.",
      "decidedAt": "2026-05-14T22:50:00.000Z"
    },
    {
      "schemaVersion": "openclaw-artifact-v1",
      "runId": "uapt-university-of-liverpool-20260514",
      "artifactType": "review_decision",
      "decisionId": "rd-liverpool-genai-lta-position",
      "claimId": "claim-liverpool-genai-lta-position",
      "decision": "approve",
      "reviewState": "agent_reviewed",
      "reviewerType": "openclaw_agent",
      "reviewer": "codex-openclaw-staged-crawl",
      "notes": "Approved because the claim is limited to the page's stated purpose for academics and students.",
      "decidedAt": "2026-05-14T22:50:00.000Z"
    },
    {
      "schemaVersion": "openclaw-artifact-v1",
      "runId": "uapt-university-of-liverpool-20260514",
      "artifactType": "review_decision",
      "decisionId": "rd-liverpool-education-unacceptable-uses",
      "claimId": "claim-liverpool-education-unacceptable-uses",
      "decision": "approve",
      "reviewState": "agent_reviewed",
      "reviewerType": "openclaw_agent",
      "reviewer": "codex-openclaw-staged-crawl",
      "notes": "Approved as a narrow restatement of the official unacceptable-uses list; not promoted as a comprehensive assessment policy.",
      "decidedAt": "2026-05-14T22:50:00.000Z"
    },
    {
      "schemaVersion": "openclaw-artifact-v1",
      "runId": "uapt-university-of-liverpool-20260514",
      "artifactType": "review_decision",
      "decisionId": "rd-liverpool-data-protection-genai",
      "claimId": "claim-liverpool-data-protection-genai",
      "decision": "approve",
      "reviewState": "agent_reviewed",
      "reviewerType": "openclaw_agent",
      "reviewer": "codex-openclaw-staged-crawl",
      "notes": "Approved because the evidence directly states GDPR compliance and restrictions on uploading personal information to AI tools.",
      "decidedAt": "2026-05-14T22:50:00.000Z"
    },
    {
      "schemaVersion": "openclaw-artifact-v1",
      "runId": "uapt-university-of-liverpool-20260514",
      "artifactType": "review_decision",
      "decisionId": "rd-liverpool-copilot-endorsed-tool",
      "claimId": "claim-liverpool-copilot-endorsed-tool",
      "decision": "approve",
      "reviewState": "agent_reviewed",
      "reviewerType": "openclaw_agent",
      "reviewer": "codex-openclaw-staged-crawl",
      "notes": "Approved because the official Foundations page directly calls Microsoft Copilot the endorsed generative AI chat tool for University work.",
      "decidedAt": "2026-05-14T22:50:00.000Z"
    },
    {
      "schemaVersion": "openclaw-artifact-v1",
      "runId": "uapt-university-of-liverpool-20260514",
      "artifactType": "review_decision",
      "decisionId": "rd-liverpool-golden-rules",
      "claimId": "claim-liverpool-golden-rules",
      "decision": "approve",
      "reviewState": "agent_reviewed",
      "reviewerType": "openclaw_agent",
      "reviewer": "codex-openclaw-staged-crawl",
      "notes": "Approved because the claim summarizes only the listed golden rules and does not add unstated enforcement language.",
      "decidedAt": "2026-05-14T22:50:00.000Z"
    },
    {
      "schemaVersion": "openclaw-artifact-v1",
      "runId": "uapt-university-of-liverpool-20260514",
      "artifactType": "review_decision",
      "decisionId": "rd-liverpool-research-guidance-accountability",
      "claimId": "claim-liverpool-research-guidance-accountability",
      "decision": "approve",
      "reviewState": "agent_reviewed",
      "reviewerType": "openclaw_agent",
      "reviewer": "codex-openclaw-staged-crawl",
      "notes": "Approved as a research-scope claim anchored to the official research guidance page.",
      "decidedAt": "2026-05-14T22:50:00.000Z"
    },
    {
      "schemaVersion": "openclaw-artifact-v1",
      "runId": "uapt-university-of-liverpool-20260514",
      "artifactType": "report_draft",
      "reportId": "report-liverpool-20260514",
      "title": "University of Liverpool AI policy staged crawl",
      "generatedAt": "2026-05-14T22:52:00.000Z",
      "draftPath": "content/reports/2026-05/university-of-liverpool-ai-policy-staged-crawl.mdx",
      "summary": "Staged official-source crawl for the University of Liverpool found central AI guidance pages covering the policy hub, learning/teaching/assessment guidance, legal/security/data protection, Microsoft Copilot, golden rules, and research guidance. Claims are staged as agent-reviewed candidates only and are not canonical.",
      "referencedClaimIds": [
        "claim-liverpool-ai-guidance-hub",
        "claim-liverpool-genai-lta-position",
        "claim-liverpool-education-unacceptable-uses",
        "claim-liverpool-data-protection-genai",
        "claim-liverpool-copilot-endorsed-tool",
        "claim-liverpool-golden-rules",
        "claim-liverpool-research-guidance-accountability"
      ],
      "publicJsonLinks": [
        "https://eduaipolicy.org/api/public/v1/claims/university-of-liverpool.json",
        "https://eduaipolicy.org/api/public/v1/universities/university-of-liverpool.json"
      ],
      "limitations": [
        "This tracker is not legal advice, not academic integrity advice, and not an official university statement unless a linked source is the university's own official page.",
        "Rejected sources include an older student news article and a repository research poster; neither was used to support current staged policy claims.",
        "Claims are narrow restatements of official pages and remain staged candidates pending any human publication workflow."
      ],
      "trackerMetadataLicense": "CC-BY-4.0",
      "sourceRightsPolicy": "Tracker metadata is open licensed. Official source documents, page text, PDFs, and other source materials retain their original rights and terms.",
      "rawArtifactPaths": []
    }
  ]
}
