{
  "schemaVersion": "openclaw-artifact-v1",
  "runId": "uapt-repair-qs-top-policy-seeds-20260506",
  "artifactType": "source_candidate",
  "sourceCandidateId": "sc-imperial-college-london-14",
  "entityType": "university",
  "entitySlug": "imperial-college-london",
  "sourceUrl": "https://www.imperial.ac.uk/media/imperial-college/administration-and-support-services/ict/public/dAIsy-use-guidance-and-process-flows-(2).pdf",
  "sourceTitle": "dAIsy Use Guidance and Process Flows",
  "sourceLanguage": "en",
  "sourceType": "other",
  "discoveryMethod": "other",
  "discoveredAt": "2026-05-06T00:47:00Z",
  "officialDomainConfidence": 1.0,
  "aiRelevanceScore": 0.85,
  "policySpecificityScore": 0.8,
  "verificationStatus": "verified",
  "verificationNotes": "PDF document with detailed dAIsy use guidance and process flows. Linked from the dAIsy main page. Provides operational guidance for the university's AI platform.",
  "robotsPolicy": "respect"
}
