{
  "schemaVersion": "openclaw-artifact-v1",
  "runId": "uapt-qs26-30-20260509",
  "artifactType": "review_decision",
  "decisionId": "rd-claim-snu-001a",
  "claimId": "claim-snu-001a",
  "decision": "approve",
  "reviewState": "agent_reviewed",
  "reviewerType": "openclaw_agent",
  "reviewer": "codex-firecrawl-review",
  "notes": "Approved after Firecrawl captured direct SNU downloads-page text confirming Korean and English PDF files for the SNU AI Guidelines; claim narrowed to remove unsupported publication-date wording.",
  "decidedAt": "2026-05-17T13:15:00.000Z"
}
