{
  "schemaVersion": "openclaw-artifact-v1",
  "runId": "uapt-kyoto-university-20260512",
  "artifactType": "evidence_candidate",
  "evidenceId": "evidence-kyoto-003",
  "claimId": "claim-kyoto-003",
  "sourceSnapshotId": "snapshot-kyoto-001",
  "sourceUrl": "https://www.oei.kyoto-u.ac.jp/%E4%BA%AC%E9%83%BD%E5%A4%A7%E5%AD%A6%E3%81%AE%E6%95%99%E8%82%B2%E5%AD%A6%E4%BF%AE%E3%81%AB%E3%81%8A%E3%81%91%E3%82%8Bai%E3%81%AE%E5%88%A9%E6%B4%BB%E7%94%A8%E3%81%AB%E3%81%A4%E3%81%84%E3%81%A6",
  "finalUrl": "https://www.oei.kyoto-u.ac.jp/%E4%BA%AC%E9%83%BD%E5%A4%A7%E5%AD%A6%E3%81%AE%E6%95%99%E8%82%B2%E5%AD%A6%E4%BF%AE%E3%81%AB%E3%81%8A%E3%81%91%E3%82%8Bai%E3%81%AE%E5%88%A9%E6%B4%BB%E7%94%A8%E3%81%AB%E3%81%A4%E3%81%84%E3%81%A6",
  "sourceTitle": "京都大学の教育・学修におけるAIの利活用について",
  "sourceLanguage": "ja",
  "snapshotHash": "a3384fe7b1a9f9929da3561d656788aff958e36cbbd41ef33d65d3fb9dd84899",
  "evidenceSnippetOriginal": "授業の履修（レポート執筆等を含む）や論文執筆に当たっては、担当教員・指導教員が示す生成AI利用方針に従うこと。",
  "evidenceSnippetDisplay": "Students must follow the generative AI use policy indicated by their instructor or supervisor for coursework and thesis writing.",
  "evidenceLocator": "京都大学の教育・学修における生成AI利用に関するガイドライン, 4(1) 学生に求められる対応: 利用方針の遵守",
  "evidenceType": "official_source",
  "relevance": 0.96,
  "rightsNote": "Tracker metadata is open licensed. Official source documents, page text, PDFs, and other source materials retain their original rights and terms.",
  "citation": {
    "citationTitle": "京都大学の教育・学修におけるAIの利活用について",
    "sourceUrl": "https://www.oei.kyoto-u.ac.jp/%E4%BA%AC%E9%83%BD%E5%A4%A7%E5%AD%A6%E3%81%AE%E6%95%99%E8%82%B2%E5%AD%A6%E4%BF%AE%E3%81%AB%E3%81%8A%E3%81%91%E3%82%8Bai%E3%81%AE%E5%88%A9%E6%B4%BB%E7%94%A8%E3%81%AB%E3%81%A4%E3%81%84%E3%81%A6",
    "publicJsonUrl": "https://eduaipolicy.org/api/public/v1/universities/kyoto-university.json",
    "canonicalUrl": "https://eduaipolicy.org/universities/kyoto-university",
    "publisher": "Kyoto University",
    "retrievedAt": "2026-05-12T15:30:00Z",
    "snapshotHash": "a3384fe7b1a9f9929da3561d656788aff958e36cbbd41ef33d65d3fb9dd84899",
    "sourceRights": "Tracker metadata is open licensed. Official source documents, page text, PDFs, and other source materials retain their original rights and terms."
  }
}
